spec_runner/__init__.py
spec_runner/executor.py
spec_runner/py.typed
spec_runner/task.py
spec_runner-0.1.0.dist-info/METADATA
spec_runner-0.1.0.dist-info/WHEEL
spec_runner-0.1.0.dist-info/entry_points.txt
spec_runner-0.1.0.dist-info/top_level.txt
spec_runner-0.1.0.dist-info/RECORD
