Metadata-Version: 2.4
Name: spec-runner
Version: 0.1.0
Summary: Task automation from markdown specs via Claude CLI
Author: Andrei
License: MIT
Project-URL: Homepage, https://github.com/pr0sto/spec-runner
Project-URL: Repository, https://github.com/pr0sto/spec-runner
Keywords: automation,tasks,claude,cli,specs,markdown
Classifier: Development Status :: 3 - Alpha
Classifier: Environment :: Console
Classifier: Intended Audience :: Developers
Classifier: License :: OSI Approved :: MIT License
Classifier: Operating System :: POSIX :: Linux
Classifier: Operating System :: MacOS
Classifier: Programming Language :: Python :: 3.10
Classifier: Programming Language :: Python :: 3.11
Classifier: Programming Language :: Python :: 3.12
Classifier: Topic :: Software Development :: Build Tools
Requires-Python: >=3.10
Requires-Dist: PyYAML>=6.0
Provides-Extra: dev
Requires-Dist: pytest>=7.0; extra == "dev"
Requires-Dist: pytest-cov>=4.0; extra == "dev"
Requires-Dist: ruff>=0.1.0; extra == "dev"
Requires-Dist: mypy>=1.0; extra == "dev"
Requires-Dist: types-PyYAML; extra == "dev"
